ec_ecology_toolbox.pypy38-pp73-x86-linux-gnu.so
ec_ecology_toolbox-0.0.8.dist-info/top_level.txt
ec_ecology_toolbox-0.0.8.dist-info/WHEEL
ec_ecology_toolbox-0.0.8.dist-info/RECORD
ec_ecology_toolbox-0.0.8.dist-info/METADATA
ec_ecology_toolbox-0.0.8.dist-info/LICENSE
